matildalink/__init__.py
matildalink/catalog.py
matildalink/cloud.py
matildalink/eenv.py
matildalink/estimator.py
matildalink/executor.py
matildalink/feat.py
matildalink/optimizer.py
matildalink/predictor.py
matildalink/provisioner.py
matildalink/work.py
matildalink-0.0.5.dist-info/METADATA
matildalink-0.0.5.dist-info/WHEEL
matildalink-0.0.5.dist-info/licenses/LICENSE
matildalink-0.0.5.dist-info/RECORD
