Metadata-Version: 2.3
Name: matildalink
Version: 0.0.5
Project-URL: Repository, https://github.com/matildalab-private/matilda-link
Author-email: Gwonsoo Che <gwonsoo.che@megazone.com>, Do Il Yoon <diyoon@megazone.com>, Frodo Hong <frodohong@megazone.com>, Sangkuk Cha <skcha@megazone.com>, Minjoo Kang <kangmj@megazone.com>
License-File: LICENSE
Classifier: Programming Language :: Python :: 3.10
Requires-Python: >=3.10
Requires-Dist: skypilot[all]
